{
  "credit": "Made with Blockbench",
  "textures": {
    "1": "laserbridges:block/laser_block_powered",
    "particle": "laserbridges:block/laser_block_powered"
  },
  "elements": [
    {
      "from": [8, 0, 0],
      "to": [8, 16, 16],
      "faces": {
        "north": {"uv": [16, 16, 0, 0], "texture": "#1", "rotation": 180, "tintindex": 0},
        "east": {"uv": [0, 0, 16, 16], "texture": "#1", "rotation": 180, "tintindex": 0},
        "south": {"uv": [0, 16, 16, 0], "texture": "#1", "rotation": 180, "tintindex": 0},
        "west": {"uv": [0, 0, 16, 16], "texture": "#1", "rotation": 180, "tintindex": 0},
        "up": {"uv": [16, 0, 0, 0], "texture": "#1", "rotation": 180, "tintindex": 0},
        "down": {"uv": [16, 0, 0, 0], "texture": "#1", "rotation": 180, "tintindex": 0}
      }
    }
  ]
}